{
    "page": {
        "id": "kctbh9vrtdwd",
        "name": "GitHub",
        "url": "https://www.githubstatus.com",
        "time_zone": "Etc/UTC",
        "updated_at": "2022-08-10T08:09:51.596Z"
    },
    "incident": {
        "id": "bd29l6zgr43g",
        "name": "Incident on 2020-02-20 21:31 UTC",
        "status": "resolved",
        "created_at": "2020-02-20T21:31:53.849Z",
        "updated_at": "2020-02-20T22:16:50.228Z",
        "monitoring_at": null,
        "resolved_at": "2020-02-20T22:16:50.209Z",
        "impact": "minor",
        "shortlink": "http://stspg.io/xm9v8qhs4rm2",
        "started_at": "2020-02-20T21:31:53.842Z",
        "page_id": "kctbh9vrtdwd",
        "incident_updates": [
            {
                "id": "005xvlfmz9j9",
                "status": "resolved",
                "body": "This incident has been resolved.",
                "incident_id": "bd29l6zgr43g",
                "created_at": "2020-02-20T22:16:50.209Z",
                "updated_at": "2020-02-20T22:16:50.209Z",
                "display_at": "2020-02-20T22:16:50.209Z",
                "affected_components": null,
                "deliver_notifications": true,
                "custom_tweet": null,
                "tweet_id": null
            },
            {
                "id": "ncn3w5zrfgch",
                "status": "investigating",
                "body": "We have implemented a fix and are monitoring service recovery.",
                "incident_id": "bd29l6zgr43g",
                "created_at": "2020-02-20T21:48:58.426Z",
                "updated_at": "2020-02-20T21:48:58.426Z",
                "display_at": "2020-02-20T21:48:58.426Z",
                "affected_components": null,
                "deliver_notifications": true,
                "custom_tweet": null,
                "tweet_id": null
            },
            {
                "id": "l20qnj3c6q63",
                "status": "investigating",
                "body": "We are investigating elevated error rates for web, api, and package registry requests.",
                "incident_id": "bd29l6zgr43g",
                "created_at": "2020-02-20T21:31:53.911Z",
                "updated_at": "2020-02-20T21:31:53.911Z",
                "display_at": "2020-02-20T21:31:53.911Z",
                "affected_components": [
                    {
                        "code": "0l2p9nhqnxpd",
                        "name": "Visit www.githubstatus.com for more information",
                        "old_status": "operational",
                        "new_status": "operational"
                    }
                ],
                "deliver_notifications": true,
                "custom_tweet": null,
                "tweet_id": null
            }
        ],
        "components": [
            {
                "id": "0l2p9nhqnxpd",
                "name": "Visit www.githubstatus.com for more information",
                "status": "operational",
                "created_at": "2018-12-05T19:39:40.838Z",
                "updated_at": "2020-04-02T21:56:21.954Z",
                "position": 4,
                "description": null,
                "showcase": false,
                "start_date": null,
                "group_id": null,
                "page_id": "kctbh9vrtdwd",
                "group": false,
                "only_show_if_degraded": false
            }
        ]
    }
}