{
    "page": {
        "id": "kctbh9vrtdwd",
        "name": "GitHub",
        "url": "https://www.githubstatus.com",
        "time_zone": "Etc/UTC",
        "updated_at": "2022-08-10T08:09:51.596Z"
    },
    "incident": {
        "id": "kx02ft2p06gl",
        "name": "Incident on 2012-02-09 20:59:02 UTC",
        "status": "resolved",
        "created_at": "2012-02-09T20:59:02.000Z",
        "updated_at": "2018-12-05T11:28:11.966Z",
        "monitoring_at": null,
        "resolved_at": "2012-02-09T20:59:02.000Z",
        "impact": "major",
        "shortlink": "http://stspg.io/39e6cf7f3",
        "started_at": "2012-02-09T20:59:02.000Z",
        "page_id": "kctbh9vrtdwd",
        "incident_updates": [
            {
                "id": "507rjykx55by",
                "status": "resolved",
                "body": "<ul><li><strong>2012-02-09 20:59:02</strong> - We're investigating connectivity problems. More info as we have it.</li><li><strong>2012-02-09 21:06:44</strong> - Services are recovering.</li></ul>",
                "incident_id": "kx02ft2p06gl",
                "created_at": "2018-12-05T11:28:11.958Z",
                "updated_at": "2018-12-05T11:28:11.958Z",
                "display_at": "2012-02-09T20:59:02.000Z",
                "affected_components": [
                    {
                        "code": "8l4ygp009s5s",
                        "name": "Git Operations",
                        "old_status": "operational",
                        "new_status": "operational"
                    }
                ],
                "deliver_notifications": false,
                "custom_tweet": null,
                "tweet_id": null
            }
        ],
        "components": [
            {
                "id": "8l4ygp009s5s",
                "name": "Git Operations",
                "status": "operational",
                "created_at": "2017-01-31T20:05:05.370Z",
                "updated_at": "2022-07-01T09:48:53.272Z",
                "position": 1,
                "description": "Performance of git clones, pulls, pushes, and associated operations",
                "showcase": false,
                "start_date": null,
                "group_id": null,
                "page_id": "kctbh9vrtdwd",
                "group": false,
                "only_show_if_degraded": false
            }
        ]
    }
}